{"config":{"output_file":null,"full_docs":false,"pub_only":true,"reachable_only":true,"distro_crate":false,"signatures":false,"borrow_data":false},"version":"0.18.1","compilation":{"directory":[47,104,111,109,101,47,109,97,98,101,122,47,100,101,118,101,108,111,112,109,101,110,116,47,114,117,115,116,47,114,117,115,116,45,120,116,101,110,115,97,47,114,117,115,116],"program":"/home/mabez/.rustup/toolchains/stable-x86_64-unknown-linux-gnu/bin/rls","arguments":["--edition=2018","--crate-name","build_script_build","src/librustc_target/build.rs","--color","never","--crate-type","bin","--emit=dep-info,link","-C","debug-assertions=off","-C","overflow-checks=on","-C","metadata=93d9dbc2bcdeb7d1","-C","extra-filename=-93d9dbc2bcdeb7d1","--out-dir","/home/mabez/development/rust/rust-xtensa/rust/src/librustc_target/target/rls/debug/build/rustc_target-93d9dbc2bcdeb7d1","-C","incremental=/home/mabez/development/rust/rust-xtensa/rust/src/librustc_target/target/rls/debug/incremental","-L","dependency=/home/mabez/development/rust/rust-xtensa/rust/src/librustc_target/target/rls/debug/deps","--error-format=json","--sysroot","/home/mabez/.rustup/toolchains/stable-x86_64-unknown-linux-gnu"],"output":[47,104,111,109,101,47,109,97,98,101,122,47,100,101,118,101,108,111,112,109,101,110,116,47,114,117,115,116,47,114,117,115,116,45,120,116,101,110,115,97,47,114,117,115,116,47,115,114,99,47,108,105,98,114,117,115,116,99,95,116,97,114,103,101,116,47,116,97,114,103,101,116,47,114,108,115,47,100,101,98,117,103,47,98,117,105,108,100,47,114,117,115,116,99,95,116,97,114,103,101,116,45,57,51,100,57,100,98,99,50,98,99,100,101,98,55,100,49,47,98,117,105,108,100,95,115,99,114,105,112,116,95,98,117,105,108,100,45,57,51,100,57,100,98,99,50,98,99,100,101,98,55,100,49]},"prelude":{"crate_id":{"name":"build_script_build","disambiguator":[15548924210449189474,4065177164664143653]},"crate_root":"src/librustc_target","external_crates":[{"file_name":"/home/mabez/development/rust/rust-xtensa/rust/src/librustc_target/build.rs","num":1,"id":{"name":"std","disambiguator":[13653490757311001470,18210972786764511751]}},{"file_name":"/home/mabez/development/rust/rust-xtensa/rust/src/librustc_target/build.rs","num":2,"id":{"name":"core","disambiguator":[10798836723055308036,13313936280221541629]}},{"file_name":"/home/mabez/development/rust/rust-xtensa/rust/src/librustc_target/build.rs","num":3,"id":{"name":"compiler_builtins","disambiguator":[4173213016744015638,3014784451015659406]}},{"file_name":"/home/mabez/development/rust/rust-xtensa/rust/src/librustc_target/build.rs","num":4,"id":{"name":"alloc","disambiguator":[11944383677982007713,15257420578295466644]}},{"file_name":"/home/mabez/development/rust/rust-xtensa/rust/src/librustc_target/build.rs","num":5,"id":{"name":"libc","disambiguator":[4959566726620691501,6146722101769139636]}},{"file_name":"/home/mabez/development/rust/rust-xtensa/rust/src/librustc_target/build.rs","num":6,"id":{"name":"unwind","disambiguator":[11525715658488109252,1561200000967009509]}},{"file_name":"/home/mabez/development/rust/rust-xtensa/rust/src/librustc_target/build.rs","num":7,"id":{"name":"panic_unwind","disambiguator":[14286758744204974931,8495317743760309751]}}],"span":{"file_name":[115,114,99,47,108,105,98,114,117,115,116,99,95,116,97,114,103,101,116,47,98,117,105,108,100,46,114,115],"byte_start":0,"byte_end":125,"line_start":1,"line_end":4,"column_start":1,"column_end":2}},"imports":[],"defs":[{"kind":"Mod","id":{"krate":0,"index":0},"span":{"file_name":[115,114,99,47,108,105,98,114,117,115,116,99,95,116,97,114,103,101,116,47,98,117,105,108,100,46,114,115],"byte_start":0,"byte_end":125,"line_start":1,"line_end":4,"column_start":1,"column_end":2},"name":"","qualname":"::","value":"src/librustc_target/build.rs","parent":null,"children":[{"krate":0,"index":2},{"krate":0,"index":4},{"krate":0,"index":6}],"decl_id":null,"docs":"","sig":null,"attributes":[]}],"impls":[],"refs":[],"macro_refs":[],"relations":[]}